data_displays/__init__.py
data_displays/code.py
data_displays-0.1.0.dist-info/METADATA
data_displays-0.1.0.dist-info/WHEEL
data_displays-0.1.0.dist-info/top_level.txt
data_displays-0.1.0.dist-info/RECORD
