Metadata-Version: 2.1
Name: data-displays
Version: 0.1.0
Summary: Asynchronus loading bars and more
Home-page: https://repl.it/@GoodCoderBadBoy/datadisplays
Author: GoodCoderBadBoy
Author-email: 
License: MIT
Platform: UNKNOWN
Classifier: License :: OSI Approved :: MIT License
Classifier: Programming Language :: Python :: 3
Classifier: Programming Language :: Python :: 3.7
